ipywidgets_game_wolf_goat_cabbage/Boat.py
ipywidgets_game_wolf_goat_cabbage/Coast.py
ipywidgets_game_wolf_goat_cabbage/Field.py
ipywidgets_game_wolf_goat_cabbage/Game.py
ipywidgets_game_wolf_goat_cabbage/WGCPlayer.py
ipywidgets_game_wolf_goat_cabbage/__init__.py
ipywidgets_game_wolf_goat_cabbage/__global__/__init__.py
ipywidgets_game_wolf_goat_cabbage/__global__/en.py
ipywidgets_game_wolf_goat_cabbage/__global__/fr.py
ipywidgets_game_wolf_goat_cabbage/images/blank.jpg
ipywidgets_game_wolf_goat_cabbage/images/cabbage.jpg
ipywidgets_game_wolf_goat_cabbage/images/gagne.jpg
ipywidgets_game_wolf_goat_cabbage/images/goat.jpg
ipywidgets_game_wolf_goat_cabbage/images/ground.jpg
ipywidgets_game_wolf_goat_cabbage/images/lost.png
ipywidgets_game_wolf_goat_cabbage/images/water.jpg
ipywidgets_game_wolf_goat_cabbage/images/win.jpg
ipywidgets_game_wolf_goat_cabbage/images/wolf.png
ipywidgets_game_wolf_goat_cabbage/images/wood.jpg
ipywidgets_game_wolf_goat_cabbage-0.2.0.dist-info/LICENSE
ipywidgets_game_wolf_goat_cabbage-0.2.0.dist-info/METADATA
ipywidgets_game_wolf_goat_cabbage-0.2.0.dist-info/WHEEL
ipywidgets_game_wolf_goat_cabbage-0.2.0.dist-info/top_level.txt
ipywidgets_game_wolf_goat_cabbage-0.2.0.dist-info/RECORD
