Metadata-Version: 2.1
Name: ipywidgets-game-wolf-goat-cabbage
Version: 0.2.0
Summary: The 'Wolf-Goat-Cabbage' game with Jupyter Notebook
Home-page: https://gitlab.u-psud.fr/edwige.gros/ipywidgets-games/tree/master/Wolf-Goat-Cabbage
Author: Edwige GROS
Author-email: edwige.gros@laposte.net
License: UNKNOWN
Platform: UNKNOWN
Classifier: Programming Language :: Python :: 3
Classifier: License :: OSI Approved :: MIT License
Classifier: Operating System :: OS Independent
Requires-Python: >=3.6
